binder/__init__.py
binder/__main__.py
binder/bin/binder
cppbinder-1.4.2.5.dist-info/RECORD
cppbinder-1.4.2.5.dist-info/WHEEL
cppbinder-1.4.2.5.dist-info/entry_points.txt
cppbinder-1.4.2.5.dist-info/METADATA
cppbinder-1.4.2.5.dist-info/licenses/LICENSE
