Metadata-Version: 2.1
Name: cppbinder
Version: 1.4.2.5
Summary: Binder, tool for automatic generation of Python bindings
Author: Rosetta Commons
Classifier: Programming Language :: Python
Classifier: Programming Language :: Python :: 2
Classifier: Programming Language :: Python :: 3
Classifier: License :: OSI Approved :: MIT License
Classifier: Operating System :: OS Independent
Project-URL: Homepage, https://github.com/RosettaCommons/binder/
Project-URL: Documentation, https://cppbinder.readthedocs.io/
Project-URL: Bug tracker, https://github.com/RosettaCommons/binder/issues/
Requires-Python: >=2.7
